aind_ophys_pipeline_utils/__init__.py
aind_ophys_pipeline_utils/demixing_utils.py
aind_ophys_pipeline_utils/dff_utils.py
aind_ophys_pipeline_utils/neuropil_correction_utils.py
aind_ophys_pipeline_utils/pipeline_util.py
aind_ophys_pipeline_utils/run_util.py
aind_ophys_pipeline_utils/segmentation_utils.py
aind_ophys_pipeline_utils/suite2p_motion_correction_utils.py
aind_ophys_pipeline_utils/trace_extraction_utils.py
aind_ophys_pipeline_utils-0.0.4.dist-info/LICENSE
aind_ophys_pipeline_utils-0.0.4.dist-info/METADATA
aind_ophys_pipeline_utils-0.0.4.dist-info/WHEEL
aind_ophys_pipeline_utils-0.0.4.dist-info/top_level.txt
aind_ophys_pipeline_utils-0.0.4.dist-info/RECORD
