Metadata-Version: 2.1
Name: aind-ophys-pipeline-utils
Version: 0.0.4
Summary: Generated from aind-library-template
Author: Allen Institute for Neural Dynamics
License: MIT
Classifier: Programming Language :: Python :: 3
Requires-Python: >=3.7
License-File: LICENSE
Requires-Dist: h5py
Requires-Dist: numpy
Requires-Dist: pandas
Requires-Dist: aind-ophys-utils
Provides-Extra: dev
Requires-Dist: black ; extra == 'dev'
Requires-Dist: coverage ; extra == 'dev'
Requires-Dist: flake8 ; extra == 'dev'
Requires-Dist: interrogate ; extra == 'dev'
Requires-Dist: isort ; extra == 'dev'
Requires-Dist: Sphinx ; extra == 'dev'
Requires-Dist: furo ; extra == 'dev'
Requires-Dist: pytest ; extra == 'dev'
